send_whatsapp_package/__init__.py
send_whatsapp_package/send_whatsapp.py
send_whatsapp_package-0.1.dist-info/LICENSE
send_whatsapp_package-0.1.dist-info/METADATA
send_whatsapp_package-0.1.dist-info/WHEEL
send_whatsapp_package-0.1.dist-info/entry_points.txt
send_whatsapp_package-0.1.dist-info/top_level.txt
send_whatsapp_package-0.1.dist-info/RECORD
