Metadata-Version: 2.1
Name: send-whatsapp-package
Version: 0.1
License-File: LICENSE
Requires-Dist: pywhatkit
Requires-Dist: pyautogui
